zaailabcorelib/__init__.py
zaailabcorelib/http_server/__init__.py
zaailabcorelib/http_server/server.py
zaailabcorelib/http_server/setting.py
zaailabcorelib/templates/run_server.sh
zaailabcorelib/thrift/TMultiplexedProcessor.py
zaailabcorelib/thrift/TRecursive.py
zaailabcorelib/thrift/TSCons.py
zaailabcorelib/thrift/TSerialization.py
zaailabcorelib/thrift/TTornado.py
zaailabcorelib/thrift/Thrift.py
zaailabcorelib/thrift/__init__.py
zaailabcorelib/thrift/compat.py
zaailabcorelib/thrift/protocol/TBase.py
zaailabcorelib/thrift/protocol/TBinaryProtocol.py
zaailabcorelib/thrift/protocol/TCompactProtocol.py
zaailabcorelib/thrift/protocol/TJSONProtocol.py
zaailabcorelib/thrift/protocol/TMultiplexedProtocol.py
zaailabcorelib/thrift/protocol/TProtocol.py
zaailabcorelib/thrift/protocol/TProtocolDecorator.py
zaailabcorelib/thrift/protocol/__init__.py
zaailabcorelib/thrift/server/THttpServer.py
zaailabcorelib/thrift/server/TNonblockingServer.py
zaailabcorelib/thrift/server/TProcessPoolServer.py
zaailabcorelib/thrift/server/TServer.py
zaailabcorelib/thrift/server/__init__.py
zaailabcorelib/thrift/transport/THttpClient.py
zaailabcorelib/thrift/transport/TSSLSocket.py
zaailabcorelib/thrift/transport/TSocket.py
zaailabcorelib/thrift/transport/TTransport.py
zaailabcorelib/thrift/transport/TTwisted.py
zaailabcorelib/thrift/transport/TZlibTransport.py
zaailabcorelib/thrift/transport/__init__.py
zaailabcorelib/thrift/transport/sslcompat.py
zaailabcorelib/thriftpool/__init__.py
zaailabcorelib/thriftpool/client.py
zaailabcorelib/thriftpool/pool.py
zaailabcorelib/zconfig/__init__.py
zaailabcorelib/zconfig/constant.py
zaailabcorelib/zconfig/zconfig.py
zaailabcorelib/zlogcentral/__init__.py
zaailabcorelib/zlogcentral/api.py
zaailabcorelib/zlogger/__init__.py
zaailabcorelib/zlogger/constant.py
zaailabcorelib/zlogger/logging.conf
zaailabcorelib/zlogger/zlogger.py
zaailabcorelib/zserver/__init__.py
zaailabcorelib/zserver/thrift/TModelPoolServer.py
zaailabcorelib/zserver/thrift/__init__.py
zaailabcorelib-0.2.1.9.dist-info/LICENSE.txt
zaailabcorelib-0.2.1.9.dist-info/METADATA
zaailabcorelib-0.2.1.9.dist-info/WHEEL
zaailabcorelib-0.2.1.9.dist-info/top_level.txt
zaailabcorelib-0.2.1.9.dist-info/RECORD
