Metadata-Version: 2.1
Name: zaailabcorelib
Version: 0.2.1.9
Summary: A useful tools inside ZAI Lab
Home-page: UNKNOWN
Author: ailabteam
License: UNKNOWN
Platform: UNKNOWN
Classifier: Programming Language :: Python :: 3
Classifier: License :: OSI Approved :: MIT License
Classifier: Operating System :: OS Independent
Requires-Dist: opencv-python
Requires-Dist: matplotlib
Requires-Dist: scipy
Requires-Dist: Image
Requires-Dist: numpy
Requires-Dist: waitress
Requires-Dist: flask-cors
